README.rst
setup.py
restub/__init__.py
restub/route.py
restub/stub.py
restub.egg-info/PKG-INFO
restub.egg-info/SOURCES.txt
restub.egg-info/dependency_links.txt
restub.egg-info/not-zip-safe
restub.egg-info/top_level.txt