Metadata-Version: 1.1
Name: restub
Version: 1.12
Summary: RESTub - REST Service Mocking
Home-page: https://github.com/everhide/restub
Author: Igor Tolkachnikov
Author-email: i.tolkachnikov@gmail.com
License: MIT
Platform: UNKNOWN
Classifier: Development Status :: 5 - Production/Stable
Classifier: Environment :: Web Environment
Classifier: Intended Audience :: Developers
Classifier: Operating System :: OS Independent
Classifier: Programming Language :: Python
Classifier: Programming Language :: Python :: 3
Classifier: Programming Language :: Python :: 3.5
Classifier: Programming Language :: Python :: 3.6
Classifier: License :: OSI Approved :: MIT License
